wafishield/__init__.py
wafishield/llm_evaluator.py
wafishield/metrics.py
wafishield/rules_engine.py
wafishield/sanitizer_engine.py
wafishield/utils.py
wafishield/wafishield.py
wafishield/patterns/__init__.py
wafishield/patterns/pii_sensitive_informations_patterns.yml
wafishield/rules/__init__.py
wafishield/rules/owasp_llm_top10.yml
wafishield/schemas/__init__.py
wafishield/schemas/patterns_schema.json
wafishield/schemas/rules_schema.json
wafishield-0.1.1.dist-info/METADATA
wafishield-0.1.1.dist-info/WHEEL
wafishield-0.1.1.dist-info/top_level.txt
wafishield-0.1.1.dist-info/RECORD
