Metadata-Version: 2.4
Name: wafishield
Version: 0.1.1
Summary: A two-layer, fully-extensible Python package for protecting LLM/agent apps against OWASP Top 10 and other evolving LLM vulnerabilities.
Home-page: https://github.com/duestack/wafishield
Author: duestack
Author-email: info@duestack.com
Classifier: Development Status :: 4 - Beta
Classifier: Intended Audience :: Developers
Classifier: Topic :: Software Development :: Libraries :: Python Modules
Classifier: License :: OSI Approved :: MIT License
Classifier: Programming Language :: Python :: 3
Classifier: Programming Language :: Python :: 3.7
Classifier: Programming Language :: Python :: 3.8
Classifier: Programming Language :: Python :: 3.9
Classifier: Programming Language :: Python :: 3.10
Classifier: Operating System :: OS Independent
Requires-Python: >=3.7
Requires-Dist: pyyaml>=6.0
Requires-Dist: regex>=2021.8.3
Requires-Dist: jsonschema>=4.0.0
Requires-Dist: requests>=2.25.0
Provides-Extra: openai
Requires-Dist: openai>=0.27.0; extra == "openai"
Provides-Extra: anthropic
Requires-Dist: anthropic>=0.2.0; extra == "anthropic"
Provides-Extra: nlp
Requires-Dist: nltk>=3.6.0; extra == "nlp"
Requires-Dist: spacy>=3.0.0; extra == "nlp"
Provides-Extra: observability
Requires-Dist: opentelemetry-api>=1.0.0; extra == "observability"
Requires-Dist: opentelemetry-sdk>=1.0.0; extra == "observability"
Requires-Dist: opentelemetry-exporter-otlp>=1.0.0; extra == "observability"
Provides-Extra: dev
Requires-Dist: pytest>=6.0.0; extra == "dev"
Requires-Dist: pytest-cov>=2.12.0; extra == "dev"
Requires-Dist: black>=21.5b2; extra == "dev"
Requires-Dist: isort>=5.9.0; extra == "dev"
Requires-Dist: mypy>=0.900; extra == "dev"
Provides-Extra: api
Requires-Dist: fastapi>=0.68.0; extra == "api"
Requires-Dist: uvicorn>=0.15.0; extra == "api"
Requires-Dist: pydantic>=1.8.2; extra == "api"
Provides-Extra: all
Requires-Dist: openai>=0.27.0; extra == "all"
Requires-Dist: anthropic>=0.2.0; extra == "all"
Requires-Dist: nltk>=3.6.0; extra == "all"
Requires-Dist: spacy>=3.0.0; extra == "all"
Requires-Dist: opentelemetry-api>=1.0.0; extra == "all"
Requires-Dist: opentelemetry-sdk>=1.0.0; extra == "all"
Requires-Dist: opentelemetry-exporter-otlp>=1.0.0; extra == "all"
Requires-Dist: fastapi>=0.68.0; extra == "all"
Requires-Dist: uvicorn>=0.15.0; extra == "all"
Requires-Dist: pydantic>=1.8.2; extra == "all"
Dynamic: author
Dynamic: author-email
Dynamic: classifier
Dynamic: description
Dynamic: description-content-type
Dynamic: home-page
Dynamic: provides-extra
Dynamic: requires-dist
Dynamic: requires-python
Dynamic: summary
